iVerilog/8bit USR/MUX41.v
module m41(out,i0,i1,i2,i3,select);

input i0,i1,i2,i3;
input[1:0] select;

output out;

wire s0_not, s1_not;

not n0(s0_not,select[0]);
not n1(s1_not,select[1]);

wire a0,a1,a2,a3;

and a0_0(a0,s1_not,s0_not,i0);
and a0_1(a1,s1_not,select[0],i1);
and a0_2(a2,select[1],s0_not,i2);
and a0_3(a3,select[1],select[0],i3);

or or_0(out,a0,a1,a2,a3);

endmodule

iVerilog/8bit USR/DFF.v
module DFF(Q,D,clk);
	
	output Q;
	input D, clk;

	wire w0, w1, w2, w3, Q_bar;
	
	nand nand00(w0, w1, w3);
	nand nand01(w1, w0, clk);
	nand nand10(w2, w1, w3, clk);
	nand nand11(w3, w2, D);
	nand nand1_0(Q, w1, Q_bar);
	nand nand1_1(Q_bar, w2, Q);

endmodule

iVerilog/8bit USR/4bit_USR.v
`include "DFF.v"
`include "MUX41.v"

module fourbUSR(out,pload,lftin,rghtin,select,clk);

output[3:0] out;

input[3:0] pload;
input lftin,rghtin;
input[1:0] select;
input clk;

wire w0,w1,w2,w3;

DFF df3(out[3],w3,clk);
DFF df2(out[2],w2,clk);
DFF df1(out[1],w1,clk);
DFF df0(out[0],w0,clk);

m41 mx3(w3,out[3],rghtin,out[2],pload[3],select);
m41 mx2(w2,out[2],out[3],out[1],pload[2],select);
m41 mx1(w1,out[1],out[2],out[0],pload[1],select);
m41 mx0(w0,out[0],out[1],lftin,pload[0],select);

endmodule

iVerilog/8bit USR/8bit_USR.v
`include "4bit_USR.v"

module eightbUSR(out,pload,lftin,rghtin,select,clk);

output[7:0] out;

input[7:0] pload;
input lftin,rghtin;
input[1:0] select;
input clk;

fourbUSR fb_usr1(out[7:4],pload[7:4],out[3],rghtin,select,clk);
fourbUSR fb_usr0(out[3:0],pload[3:0],lftin,out[4],select,clk);

endmodule

iVerilog/8bit USR/8bit_USR_tb.v
`include "8bit_USR.v"

module top;

wire[7:0] out;
reg[7:0] pload;
reg lftin,rghtin;
reg[1:0] select;
reg clk;

eightbUSR usr0(out,pload,lftin,rghtin,select,clk);

always #5 clk = !clk;

initial
begin	

		clk =0;select = 2'b11; pload = 8'b0000_0000; lftin = 1'b0; rghtin = 1'b0; 

		#10 select = 2'b11; pload = 8'b100_0001;

		#10 select = 2'b11; pload = 8'b1000_1110;

		#10 select = 2'b11; pload = 8'b1010_0101; 

		#10 select = 2'b01; rghtin = 1'b1; 

		#10 select = 2'b01; rghtin = 1'b1; 

		#10 select = 2'b01; rghtin = 1'b0; 

		#10 select = 2'b01; rghtin = 1'b0; 

		#10 select = 2'b01; rghtin = 1'b0; 
		
		#10 select = 2'b00;

		#10 select = 2'b10; lftin = 1'b1;

		#10 select = 2'b10; lftin = 1'b1;

		#10 select = 2'b10; lftin = 1'b1;

		#10 select = 2'b10; lftin = 1'b0;

		#10 select = 2'b10; lftin = 1'b0;


end

initial
#150 $finish;

initial
begin

	$monitor($time,"	SelectInputs = %2b ---- Parallelload = %8b --- lftin = %b, rghtin = %b, -- out = %8b",select,pload,lftin,rghtin,out);	
	$dumpfile("USR.vcd");      
	$dumpvars;

end                        
    
endmodule

iVerilog/8bit USR/USR.vcd
$date
	Thu Aug 27 15:31:22 2020
$end
$version
	Icarus Verilog
$end
$timescale
	1s
$end
$scope module top $end
$var wire 8 ! out [7:0] $end
$var reg 1 " clk $end
$var reg 1 # lftin $end
$var reg 8 $ pload [7:0] $end
$var reg 1 % rghtin $end
$var reg 2 & select [1:0] $end
$scope module usr0 $end
$var wire 1 " clk $end
$var wire 1 # lftin $end
$var wire 8 ' pload [7:0] $end
$var wire 1 % rghtin $end
$var wire 2 ( select [1:0] $end
$var wire 8 ) out [7:0] $end
$scope module fb_usr0 $end
$var wire 1 " clk $end
$var wire 1 # lftin $end
$var wire 4 * pload [3:0] $end
$var wire 1 + rghtin $end
$var wire 2 , select [1:0] $end
$var wire 1 - w3 $end
$var wire 1 . w2 $end
$var wire 1 / w1 $end
$var wire 1 0 w0 $end
$var wire 4 1 out [3:0] $end
$scope module df0 $end
$var wire 1 2 Q $end
$var wire 1 3 Q_bar $end
$var wire 1 " clk $end
$var wire 1 4 w0 $end
$var wire 1 5 w1 $end
$var wire 1 6 w2 $end
$var wire 1 7 w3 $end
$var wire 1 0 D $end
$upscope $end
$scope module df1 $end
$var wire 1 8 Q $end
$var wire 1 9 Q_bar $end
$var wire 1 " clk $end
$var wire 1 : w0 $end
$var wire 1 ; w1 $end
$var wire 1 < w2 $end
$var wire 1 = w3 $end
$var wire 1 / D $end
$upscope $end
$scope module df2 $end
$var wire 1 > Q $end
$var wire 1 ? Q_bar $end
$var wire 1 " clk $end
$var wire 1 @ w0 $end
$var wire 1 A w1 $end
$var wire 1 B w2 $end
$var wire 1 C w3 $end
$var wire 1 . D $end
$upscope $end
$scope module df3 $end
$var wire 1 D Q $end
$var wire 1 E Q_bar $end
$var wire 1 " clk $end
$var wire 1 F w0 $end
$var wire 1 G w1 $end
$var wire 1 H w2 $end
$var wire 1 I w3 $end
$var wire 1 - D $end
$upscope $end
$scope module mx0 $end
$var wire 1 J a0 $end
$var wire 1 K a1 $end
$var wire 1 L a2 $end
$var wire 1 M a3 $end
$var wire 1 N i0 $end
$var wire 1 O i1 $end
$var wire 1 # i2 $end
$var wire 1 P i3 $end
$var wire 1 0 out $end
$var wire 1 Q s0_not $end
$var wire 1 R s1_not $end
$var wire 2 S select [1:0] $end
$upscope $end
$scope module mx1 $end
$var wire 1 T a0 $end
$var wire 1 U a1 $end
$var wire 1 V a2 $end
$var wire 1 W a3 $end
$var wire 1 X i0 $end
$var wire 1 Y i1 $end
$var wire 1 Z i2 $end
$var wire 1 [ i3 $end
$var wire 1 / out $end
$var wire 1 \ s0_not $end
$var wire 1 ] s1_not $end
$var wire 2 ^ select [1:0] $end
$upscope $end
$scope module mx2 $end
$var wire 1 _ a0 $end
$var wire 1 ` a1 $end
$var wire 1 a a2 $end
$var wire 1 b a3 $end
$var wire 1 c i0 $end
$var wire 1 d i1 $end
$var wire 1 e i2 $end
$var wire 1 f i3 $end
$var wire 1 . out $end
$var wire 1 g s0_not $end
$var wire 1 h s1_not $end
$var wire 2 i select [1:0] $end
$upscope $end
$scope module mx3 $end
$var wire 1 j a0 $end
$var wire 1 k a1 $end
$var wire 1 l a2 $end
$var wire 1 m a3 $end
$var wire 1 n i0 $end
$var wire 1 + i1 $end
$var wire 1 o i2 $end
$var wire 1 p i3 $end
$var wire 1 - out $end
$var wire 1 q s0_not $end
$var wire 1 r s1_not $end
$var wire 2 s select [1:0] $end
$upscope $end
$upscope $end
$scope module fb_usr1 $end
$var wire 1 " clk $end
$var wire 1 t lftin $end
$var wire 4 u pload [3:0] $end
$var wire 1 % rghtin $end
$var wire 2 v select [1:0] $end
$var wire 1 w w3 $end
$var wire 1 x w2 $end
$var wire 1 y w1 $end
$var wire 1 z w0 $end
$var wire 4 { out [3:0] $end
$scope module df0 $end
$var wire 1 | Q $end
$var wire 1 } Q_bar $end
$var wire 1 " clk $end
$var wire 1 ~ w0 $end
$var wire 1 !" w1 $end
$var wire 1 "" w2 $end
$var wire 1 #" w3 $end
$var wire 1 z D $end
$upscope $end
$scope module df1 $end
$var wire 1 $" Q $end
$var wire 1 %" Q_bar $end
$var wire 1 " clk $end
$var wire 1 &" w0 $end
$var wire 1 '" w1 $end
$var wire 1 (" w2 $end
$var wire 1 )" w3 $end
$var wire 1 y D $end
$upscope $end
$scope module df2 $end
$var wire 1 *" Q $end
$var wire 1 +" Q_bar $end
$var wire 1 " clk $end
$var wire 1 ," w0 $end
$var wire 1 -" w1 $end
$var wire 1 ." w2 $end
$var wire 1 /" w3 $end
$var wire 1 x D $end
$upscope $end
$scope module df3 $end
$var wire 1 0" Q $end
$var wire 1 1" Q_bar $end
$var wire 1 " clk $end
$var wire 1 2" w0 $end
$var wire 1 3" w1 $end
$var wire 1 4" w2 $end
$var wire 1 5" w3 $end
$var wire 1 w D $end
$upscope $end
$scope module mx0 $end
$var wire 1 6" a0 $end
$var wire 1 7" a1 $end
$var wire 1 8" a2 $end
$var wire 1 9" a3 $end
$var wire 1 :" i0 $end
$var wire 1 ;" i1 $end
$var wire 1 t i2 $end
$var wire 1 <" i3 $end
$var wire 1 z out $end
$var wire 1 =" s0_not $end
$var wire 1 >" s1_not $end
$var wire 2 ?" select [1:0] $end
$upscope $end
$scope module mx1 $end
$var wire 1 @" a0 $end
$var wire 1 A" a1 $end
$var wire 1 B" a2 $end
$var wire 1 C" a3 $end
$var wire 1 D" i0 $end
$var wire 1 E" i1 $end
$var wire 1 F" i2 $end
$var wire 1 G" i3 $end
$var wire 1 y out $end
$var wire 1 H" s0_not $end
$var wire 1 I" s1_not $end
$var wire 2 J" select [1:0] $end
$upscope $end
$scope module mx2 $end
$var wire 1 K" a0 $end
$var wire 1 L" a1 $end
$var wire 1 M" a2 $end
$var wire 1 N" a3 $end
$var wire 1 O" i0 $end
$var wire 1 P" i1 $end
$var wire 1 Q" i2 $end
$var wire 1 R" i3 $end
$var wire 1 x out $end
$var wire 1 S" s0_not $end
$var wire 1 T" s1_not $end
$var wire 2 U" select [1:0] $end
$upscope $end
$scope module mx3 $end
$var wire 1 V" a0 $end
$var wire 1 W" a1 $end
$var wire 1 X" a2 $end
$var wire 1 Y" a3 $end
$var wire 1 Z" i0 $end
$var wire 1 % i1 $end
$var wire 1 [" i2 $end
$var wire 1 \" i3 $end
$var wire 1 w out $end
$var wire 1 ]" s0_not $end
$var wire 1 ^" s1_not $end
$var wire 2 _" select [1:0] $end
$upscope $end
$upscope $end
$upscope $end
$upscope $end
$enddefinitions $end
#0
$dumpvars
b11 _"
0^"
0]"
0\"
x["
xZ"
0Y"
0X"
0W"
0V"
b11 U"
0T"
0S"
0R"
xQ"
xP"
xO"
0N"
0M"
0L"
0K"
b11 J"
0I"
0H"
0G"
xF"
xE"
xD"
0C"
0B"
0A"
0@"
b11 ?"
0>"
0="
0<"
x;"
x:"
09"
08"
07"
06"
15"
14"
13"
02"
x1"
x0"
1/"
1."
1-"
0,"
x+"
x*"
1)"
1("
1'"
0&"
x%"
x$"
1#"
1""
1!"
0~
x}
x|
bx {
0z
0y
0x
0w
b11 v
b0 u
xt
b11 s
0r
0q
0p
xo
xn
0m
0l
0k
0j
b11 i
0h
0g
0f
xe
xd
xc
0b
0a
0`
0_
b11 ^
0]
0\
0[
xZ
xY
xX
0W
0V
0U
0T
b11 S
0R
0Q
0P
xO
xN
0M
0L
0K
0J
1I
1H
1G
0F
xE
xD
1C
1B
1A
0@
x?
x>
1=
1<
1;
0:
x9
x8
17
16
15
04
x3
x2
bx 1
00
0/
0.
0-
b11 ,
x+
b0 *
bx )
b11 (
b0 '
b11 &
0%
b0 $
0#
0"
bx !
$end
#5
0Z
0N
0e
0X
0O
0o
0c
0Y
0n
0d
0t
0F"
0:"
0+
0Q"
0D"
0;"
0["
0O"
0E"
0Z"
0P"
02
08
0>
b0 1
0D
0|
0$"
0*"
b0 !
b0 )
b0 {
00"
13
19
1?
1E
1}
1%"
1+"
11"
06
0<
0B
0H
0""
0("
0."
04"
1"
#10
1,"
14
0/"
07
1x
10
1N"
1M
1R"
1P
16
1<
1B
1H
1""
1("
1."
14"
b100 u
b1 *
0"
b1000001 $
b1000001 '
#15
03
1Z
1N
0+"
1["
1O"
1E"
b1 1
12
b1000001 !
b1000001 )
b100 {
1*"
05
0<
0B
0H
0""
0("
0-"
04"
1"
#20
12"
0,"
1F
1@
1:
04
05"
1/"
0I
0C
0=
17
1w
0x
1-
1.
1/
00
1Y"
0N"
1m
1b
1W
0M
1\"
0R"
1p
1f
1[
0P
15
1<
1B
1H
1""
1("
1-"
14"
b1000 u
b1110 *
0"
b10001110 $
b10001110 '
#25
0Z
0N
0["
0O"
0E"
02
09
1e
1X
1O
0?
1o
1c
1Y
0E
1n
1d
1t
0*"
01"
1Z"
1P"
13
18
1>
b1110 1
1D
1+"
b10001110 !
b10001110 )
b1000 {
10"
06
0;
0A
0G
0""
0("
0."
03"
1"
#30
1&"
0F
0:
14
0)"
1I
1=
07
1y
0-
0/
10
1C"
0m
0W
1M
1G"
0p
0[
1P
16
1;
1A
1G
1""
1("
1."
13"
b1010 u
b101 *
0"
b10100101 $
b10100101 '
#35
0e
0X
0O
0n
0d
0t
03
1Z
1N
08
0D
0%"
1Q"
1D"
1;"
b101 1
12
19
1E
b10100101 !
b10100101 )
b1010 {
1$"
05
0<
0A
0H
0""
0'"
0."
03"
1"
#40
1:
1~
1,"
04
0=
0@
0#"
0&"
0/"
12"
17
1/
1C
1z
1)"
1x
05"
00
1U
0.
17"
0y
1L"
1W"
1w
1R
0M
1]
1h
0b
1r
1>"
1I"
0C"
1T"
1^"
0Y"
15
1<
1A
1H
1""
1'"
1."
13"
0"
1%
b1 &
b1 (
b1 ,
b1 S
b1 ^
b1 i
b1 s
b1 v
b1 ?"
b1 J"
b1 U"
b1 _"
#45
1=
1#"
0/
0z
10
0U
1-
07"
1y
0Z
0N
1K
0o
0c
0Y
1k
0Q"
0D"
0;"
1A"
02
09
1e
1X
1O
0>
0}
1F"
1:"
1+
0$"
0+"
1["
1O"
1E"
13
b10 1
18
1?
1|
1%"
b11010010 !
b11010010 )
b1101 {
1*"
06
0;
0B
0H
0!"
0("
0-"
03"
1"
#50
14
1F
1&"
07
0:
0I
0~
0)"
16
1;
1B
1H
1!"
1("
1-"
13"
0"
#55
17
1I
00
0-
0K
1.
0k
1z
0e
0X
0O
1`
0F"
0:"
0+
17"
03
1Z
1N
08
0E
1n
1d
1t
0|
0%"
1Q"
1D"
1;"
12
19
b1001 1
1D
1}
b11101001 !
b11101001 )
b1110 {
1$"
05
0<
0B
0G
0""
0'"
0-"
03"
1"
#60
02"
1@
1~
15"
04
0C
0F
0#"
0w
15
1<
1B
1G
1""
1'"
1-"
13"
0W"
0"
0%
#65
1C
1/"
0.
0x
1/
0`
1-
0L"
0Z
0N
1U
0n
0d
0t
1k
0Z"
0P"
02
0?
1o
1c
1Y
0D
0}
1F"
1:"
1+
00"
13
b100 1
1>
1E
b1110100 !
b1110100 )
b111 {
1|
11"
06
0<
0A
0H
0!"
0'"
0-"
04"
1"
#70
1:
1F
0=
0@
0I
0,"
16
1<
1A
1H
1!"
1'"
1-"
14"
0"
#75
1=
1)"
0/
0y
10
0U
1.
0A"
1K
0o
0c
0Y
1`
0["
0O"
0E"
09
1e
1X
1O
0>
0E
1n
1d
1t
b11 {
0*"
18
1?
b111010 !
b111010 )
b1010 1
1D
1+"
06
0;
0B
0G
0!"
0'"
0."
04"
1"
#80
14
1@
07
0:
0C
0&"
16
1;
1B
1G
1!"
1'"
1."
14"
0"
#85
17
1#"
00
0z
0K
1/
07"
0e
0X
0O
1U
0Q"
0D"
0;"
03
1Z
1N
08
0?
1o
1c
1Y
b1 {
0$"
12
19
b11101 !
b11101 )
b1101 1
1>
1%"
05
0<
0A
0G
0!"
0("
0."
04"
1"
#90
07
1@
1F
0#"
10
0C
0I
1z
0:
1J
0/
1_
1.
1j
1-
16"
14
1=
1~
1Q
1\
0U
1g
0`
1q
0k
1="
1H"
1S"
1]"
15
1<
1A
1G
1!"
1("
1."
14"
0"
b0 &
b0 (
b0 ,
b0 S
b0 ^
b0 i
b0 s
b0 v
b0 ?"
b0 J"
b0 U"
b0 _"
#95
05
0<
0A
0G
0!"
0("
0."
04"
1"
#100
0@
1:
1C
1&"
0=
0.
0)"
0J
1/
0_
0j
06"
1y
0R
0]
1V
0h
0r
1l
0>"
18"
0I"
1B"
0T"
0^"
15
1<
1A
1G
1!"
1("
1."
14"
1L
0"
1#
b10 &
b10 (
b10 ,
b10 S
b10 ^
b10 i
b10 s
b10 v
b10 ?"
b10 J"
b10 U"
b10 _"
#105
1I
0-
1.
0l
1x
1a
0o
0c
0Y
1M"
09
1e
1X
1O
0>
0%"
1Q"
1D"
1;"
b1011 1
18
1?
b111011 !
b111011 )
b11 {
1$"
05
0;
0B
0G
0!"
0'"
0."
04"
1"
#110
1@
1,"
0C
0F
0/"
15
1;
1B
1G
1!"
1'"
1."
14"
0"
#115
1#"
0z
1-
08"
1w
1l
0n
0d
0t
1X"
0?
1o
1c
1Y
0D
0+"
1["
1O"
1E"
b111 1
1>
1E
b1110111 !
b1110111 )
b111 {
1*"
05
0;
0A
0H
0!"
0'"
0-"
04"
1"
#120
1F
12"
0I
0~
05"
15
1;
1A
1H
1!"
1'"
1-"
14"
0"
#125
1)"
0y
1z
0B"
18"
0F"
0:"
0+
0E
1n
1d
1t
0|
01"
1Z"
1P"
b1111 1
1D
1}
b11101111 !
b11101111 )
b1110 {
10"
05
0;
0A
0G
0""
0'"
0-"
03"
1"
#130
04
1~
17
0#"
0&"
00
15
1;
1A
1G
1""
1'"
1-"
13"
0L
0"
0#
#135
1=
1/"
0/
0x
0V
1y
0M"
0Z
0N
1B"
0Q"
0D"
0;"
b1110 1
02
0}
1F"
1:"
1+
0$"
13
b11011110 !
b11011110 )
b1101 {
1|
1%"
06
0;
0A
0G
0!"
0("
0-"
03"
1"
#140
1&"
0:
0)"
0,"
16
1;
1A
1G
1!"
1("
1-"
13"
0"
#145
1C
15"
0.
0w
0a
1x
0X"
0e
0X
0O
1M"
0["
0O"
0E"
b1100 1
08
0%"
1Q"
1D"
1;"
0*"
19
b10111100 !
b10111100 )
b1011 {
1$"
1+"
06
0<
0A
0G
0!"
0'"
0."
03"
1"
#150
1,"
0@
0/"
02"
16
1<
1A
1G
1!"
1'"
1."
13"
0"
